nestedlist/__init__.py
nestedlist/core.py
flatlist-0.1.0.dist-info/METADATA
flatlist-0.1.0.dist-info/WHEEL
flatlist-0.1.0.dist-info/top_level.txt
flatlist-0.1.0.dist-info/RECORD
