Metadata-Version: 2.4
Name: flatlist
Version: 0.1.0
Summary: A simple Python package to flat a list
Author-email: SAJAL <sajalkumar801@gmail.com>
License: MIT
Classifier: Programming Language :: Python :: 3
Classifier: License :: OSI Approved :: MIT License
Classifier: Operating System :: OS Independent
Requires-Python: >=3.8
